ZEO/ClientStorage.py
ZEO/Exceptions.py
ZEO/StorageServer.py
ZEO/TransactionBuffer.py
ZEO/__init__.py
ZEO/_compat.py
ZEO/_forker.py
ZEO/cache.py
ZEO/component.xml
ZEO/interfaces.py
ZEO/monitor.py
ZEO/nagios.py
ZEO/nagios.rst
ZEO/runzeo.py
ZEO/schema.xml
ZEO/server.xml
ZEO/shortrepr.py
ZEO/util.py
ZEO/version.txt
ZEO/zconfig.py
ZEO/zeoctl.py
ZEO/zeoctl.xml
ZEO/asyncio/README.rst
ZEO/asyncio/__init__.py
ZEO/asyncio/_futures.pyx
ZEO/asyncio/_smp.pyx
ZEO/asyncio/base.py
ZEO/asyncio/client.py
ZEO/asyncio/compat.py
ZEO/asyncio/futures.py
ZEO/asyncio/marshal.py
ZEO/asyncio/server.py
ZEO/asyncio/smp.py
ZEO/asyncio/testing.py
ZEO/asyncio/tests.py
ZEO/scripts/README.txt
ZEO/scripts/__init__.py
ZEO/scripts/cache_simul.py
ZEO/scripts/cache_stats.py
ZEO/scripts/parsezeolog.py
ZEO/scripts/tests.py
ZEO/scripts/timeout.py
ZEO/scripts/zeopack.py
ZEO/scripts/zeopack.test
ZEO/scripts/zeoqueue.py
ZEO/scripts/zeoreplay.py
ZEO/scripts/zeoserverlog.py
ZEO/scripts/zeoup.py
ZEO/tests/Cache.py
ZEO/tests/CommitLockTests.py
ZEO/tests/ConnectionTests.py
ZEO/tests/InvalidationTests.py
ZEO/tests/IterationTests.py
ZEO/tests/TestThread.py
ZEO/tests/ThreadTests.py
ZEO/tests/__init__.py
ZEO/tests/client-config.test
ZEO/tests/client.pem
ZEO/tests/client_key.pem
ZEO/tests/component.xml
ZEO/tests/drop_cache_rather_than_verify.txt
ZEO/tests/dynamic_server_ports.test
ZEO/tests/forker.py
ZEO/tests/invalidation-age.txt
ZEO/tests/new_addr.test
ZEO/tests/protocols.test
ZEO/tests/racetest.py
ZEO/tests/server.pem
ZEO/tests/server.pem.csr
ZEO/tests/server_key.pem
ZEO/tests/serverpw.pem
ZEO/tests/serverpw_key.pem
ZEO/tests/servertesting.py
ZEO/tests/speed.py
ZEO/tests/stress.py
ZEO/tests/testConfig.py
ZEO/tests/testConnection.py
ZEO/tests/testConversionSupport.py
ZEO/tests/testTransactionBuffer.py
ZEO/tests/testZEO.py
ZEO/tests/testZEO2.py
ZEO/tests/testZEOOptions.py
ZEO/tests/testZEOServer.py
ZEO/tests/test_cache.py
ZEO/tests/test_client_credentials.py
ZEO/tests/test_client_side_conflict_resolution.py
zeo-6.1.dist-info/COPYING
zeo-6.1.dist-info/LICENSE.txt
zeo-6.1.dist-info/METADATA
zeo-6.1.dist-info/WHEEL
zeo-6.1.dist-info/entry_points.txt
zeo-6.1.dist-info/top_level.txt
zeo-6.1.dist-info/RECORD
