Metadata-Version: 2.2
Name: ZEO
Version: 6.1
Summary: ZEO - Single-server client-server database server for ZODB
Home-page: https://github.com/zopefoundation/ZEO
Author: Zope Foundation and Contributors
Author-email: zodb@googlegroups.com
License: ZPL-2.1
Keywords: database,zodb
Platform: any
Classifier: Intended Audience :: Developers
Classifier: License :: OSI Approved :: Zope Public License
Classifier: Programming Language :: Python :: 3
Classifier: Programming Language :: Python :: 3.9
Classifier: Programming Language :: Python :: 3.10
Classifier: Programming Language :: Python :: 3.11
Classifier: Programming Language :: Python :: 3.12
Classifier: Programming Language :: Python :: 3.13
Classifier: Programming Language :: Python :: Implementation :: CPython
Classifier: Programming Language :: Python :: Implementation :: PyPy
Classifier: Topic :: Database
Classifier: Topic :: Software Development :: Libraries :: Python Modules
Classifier: Operating System :: Microsoft :: Windows
Classifier: Operating System :: Unix
Classifier: Framework :: ZODB
Requires-Python: >=3.9
License-File: LICENSE.txt
License-File: COPYING
Requires-Dist: ZODB>=5.1.1
Requires-Dist: transaction>=2.0.3
Requires-Dist: persistent>=4.1.0
Requires-Dist: zc.lockfile
Requires-Dist: ZConfig
Requires-Dist: zdaemon
Requires-Dist: zope.interface
Provides-Extra: test
Requires-Dist: ZConfig; extra == "test"
Requires-Dist: ZODB>=5.5.1; extra == "test"
Requires-Dist: ZopeUndo; extra == "test"
Requires-Dist: zope.testing; extra == "test"
Requires-Dist: transaction; extra == "test"
Requires-Dist: msgpack; extra == "test"
Requires-Dist: zdaemon; extra == "test"
Requires-Dist: zope.testrunner; extra == "test"
Provides-Extra: uvloop
Requires-Dist: uvloop>=0.5.1; extra == "uvloop"
Provides-Extra: msgpack
Requires-Dist: msgpack-python; extra == "msgpack"
Provides-Extra: docs
Requires-Dist: Sphinx; extra == "docs"
Requires-Dist: repoze.sphinx.autointerface; extra == "docs"
Requires-Dist: sphinx_rtd_theme; extra == "docs"
Dynamic: author
Dynamic: author-email
Dynamic: classifier
Dynamic: description
Dynamic: home-page
Dynamic: keywords
Dynamic: license
Dynamic: platform
Dynamic: provides-extra
Dynamic: requires-dist
Dynamic: requires-python
Dynamic: summary
